[{"arrondissement_num": 20, "insee_code": "75120", "arrondissement": "20e \u2014 M\u00e9nilmontant", "year": 1968, "population": 188921.0, "density": 31592.1, "persons_per_dwelling": 2.3}, {"arrondissement_num": 20, "insee_code": "75120", "arrondissement": "20e \u2014 M\u00e9nilmontant", "year": 1975, "population": 175795.0, "density": 29397.2, "persons_per_dwelling": 2.1}, {"arrondissement_num": 20, "insee_code": "75120", "arrondissement": "20e \u2014 M\u00e9nilmontant", "year": 1982, "population": 171971.0, "density": 28757.7, "persons_per_dwelling": 2.03}, {"arrondissement_num": 20, "insee_code": "75120", "arrondissement": "20e \u2014 M\u00e9nilmontant", "year": 1990, "population": 184478.0, "density": 30849.2, "persons_per_dwelling": 2.04}, {"arrondissement_num": 20, "insee_code": "75120", "arrondissement": "20e \u2014 M\u00e9nilmontant", "year": 1999, "population": 182952.0, "density": 30594.0, "persons_per_dwelling": 1.98}, {"arrondissement_num": 20, "insee_code": "75120", "arrondissement": "20e \u2014 M\u00e9nilmontant", "year": 2006, "population": 193205.0, "density": 32308.5, "persons_per_dwelling": 1.99}, {"arrondissement_num": 20, "insee_code": "75120", "arrondissement": "20e \u2014 M\u00e9nilmontant", "year": 2011, "population": 198042.0, "density": 33117.4, "persons_per_dwelling": 2.01}, {"arrondissement_num": 20, "insee_code": "75120", "arrondissement": "20e \u2014 M\u00e9nilmontant", "year": 2016, "population": 195604.0, "density": 32709.7, "persons_per_dwelling": 1.97}, {"arrondissement_num": 20, "insee_code": "75120", "arrondissement": "20e \u2014 M\u00e9nilmontant", "year": 2022, "population": 187694.0, "density": 31387.0, "persons_per_dwelling": 1.9}]